{
  "coverage": "76.31%",
  "expectCount": 76,
  "actualCount": 58,
  "files": {
    "src/App.js": {
      "expectCount": 11,
      "actualCount": 9,
      "undocumentLines": [
        12,
        23
      ]
    },
    "src/middlewares/handleError.js": {
      "expectCount": 5,
      "actualCount": 1,
      "undocumentLines": [
        1,
        17,
        23,
        35
      ]
    },
    "src/routes/Route.js": {
      "expectCount": 45,
      "actualCount": 44,
      "undocumentLines": [
        11
      ]
    },
    "src/routes/RouteDecorators.js": {
      "expectCount": 10,
      "actualCount": 1,
      "undocumentLines": [
        28,
        34,
        48,
        63,
        87,
        93,
        99,
        105,
        111
      ]
    },
    "src/utils/ErrorApp.js": {
      "expectCount": 5,
      "actualCount": 3,
      "undocumentLines": [
        1,
        2
      ]
    }
  }
}